{
    "entities": [
        {
            "albedoPath": "gamedata/assets/textures/SciFiHelmet_BaseColor.png",
            "modelPath": "gamedata/assets/models/SciFiHelmet.gltf",
            "name": "Sci Fi Helmet",
            "position": [
                -2.9681973457336426,
                0.017517708241939545,
                -0.030505657196044922
            ],
            "renderable": true,
            "rotation": [
                0.0,
                -0.0,
                0.0
            ],
            "scale": [
                0.999602198600769,
                0.9999974966049194,
                0.9999998807907104
            ]
        },
        {
            "albedoPath": "gamedata/assets/textures/test_texture.png",
            "modelPath": "gamedata/assets/models/Cube.gltf",
            "name": "Sorin Cube",
            "position": [
                3.0,
                0.0,
                0.0
            ],
            "renderable": true,
            "rotation": [
                0.0,
                0.0,
                0.0
            ],
            "scale": [
                1.0,
                1.0,
                1.0
            ]
        },
        {
            "albedoPath": "gamedata/assets/textures/Suzanne_BaseColor.png",
            "modelPath": "gamedata/assets/models/Suzanne.gltf",
            "name": "Suzanne",
            "position": [
                0.0,
                0.0,
                0.0
            ],
            "renderable": true,
            "rotation": [
                0.0,
                0.0,
                0.0
            ],
            "scale": [
                1.0,
                1.0,
                1.0
            ]
        }
    ],
    "sceneName": "Models Scene"
}
